README.rst
setup.py
pypw/__init__.py
pypw/pypw.py
pypw.egg-info/PKG-INFO
pypw.egg-info/SOURCES.txt
pypw.egg-info/dependency_links.txt
pypw.egg-info/entry_points.txt
pypw.egg-info/top_level.txt