Metadata-Version: 1.0
Name: pypw
Version: 1.0.0
Summary: Generates a random password.
Home-page: https://github.com/Dinoshauer/PyPW
Author: Kasper Jacobsen
Author-email: k@mackwerk.dk
License: MIT
Platform: UNKNOWN
